eubi_bridge/__init__.py
eubi_bridge/cli.py
eubi_bridge/ebridge.py
eubi_bridge/ebridge_base.py
eubi_bridge/fileset_io.py
eubi_bridge/base/__init__.py
eubi_bridge/base/czi_reader.py
eubi_bridge/base/data_manager.py
eubi_bridge/base/readers.py
eubi_bridge/base/scale.py
eubi_bridge/base/writers.py
eubi_bridge/ngff/__init__.py
eubi_bridge/ngff/defaults.py
eubi_bridge/ngff/multiscales.py
eubi_bridge/utils/__init__.py
eubi_bridge/utils/convenience.py
eubi_bridge/utils/dask_client_plugins.py
eubi_bridge/utils/metadata_utils.py
eubi_bridge-0.0.7.dist-info/licenses/LICENSE
eubi_bridge-0.0.7.dist-info/METADATA
eubi_bridge-0.0.7.dist-info/WHEEL
eubi_bridge-0.0.7.dist-info/entry_points.txt
eubi_bridge-0.0.7.dist-info/top_level.txt
eubi_bridge-0.0.7.dist-info/RECORD
