Metadata-Version: 2.4
Name: eubi_bridge
Version: 0.0.7
Summary: A package for converting datasets to OME-Zarr format.
Home-page: https://github.com/Euro-BioImaging/EuBI-Bridge
Author: Bugra Özdemir
Author-email: bugraa.ozdemir@gmail.com
License: MIT
Requires-Python: >=3.11,<3.13
License-File: LICENSE
Requires-Dist: aicspylibczi>=0.0.0
Requires-Dist: asciitree>=0.3.3
Requires-Dist: bfio>=0.0.0
Requires-Dist: bioformats_jar>=0.0.0
Requires-Dist: bioio-base>=0.0.0
Requires-Dist: bioio-bioformats==1.1.0
Requires-Dist: bioio-czi==2.1.0
Requires-Dist: bioio-imageio==1.1.0
Requires-Dist: bioio-lif==1.1.0
Requires-Dist: bioio-nd2==1.1.0
Requires-Dist: bioio-ome-tiff-fork-by-bugra==0.0.1b2
Requires-Dist: bioio-tifffile-fork-by-bugra>=0.0.1b2
Requires-Dist: cmake==4.0.2
Requires-Dist: dask>=2024.12.1
Requires-Dist: dask-jobqueue>=0.0.0
Requires-Dist: distributed>=2024.12.1
Requires-Dist: elementpath==5.0.1
Requires-Dist: fasteners==0.19
Requires-Dist: fire>=0.0.0
Requires-Dist: imageio==2.27.0
Requires-Dist: imageio-ffmpeg==0.6.0
Requires-Dist: natsort>=0.0.0
Requires-Dist: nd2>=0.0.0
Requires-Dist: numpy>=0.0.0
Requires-Dist: pydantic>=0.0.0
Requires-Dist: pylibczirw>=0.0.0
Requires-Dist: readlif==0.6.5
Requires-Dist: s3fs>=0.0.0
Requires-Dist: scipy>=1.8
Requires-Dist: tensorstore>=0.0.0
Requires-Dist: tifffile>=2025.5.21
Requires-Dist: validators==0.35.0
Requires-Dist: xarray>=0.0.0
Requires-Dist: xmlschema>=0.0.0
Requires-Dist: xmltodict==0.14.2
Requires-Dist: zarr>=3.0
Requires-Dist: zstandard>=0.0.0
Provides-Extra: cuda11
Requires-Dist: cupy-cuda11x; extra == "cuda11"
Provides-Extra: cuda12
Requires-Dist: cupy-cuda12x; extra == "cuda12"
Dynamic: author
Dynamic: author-email
Dynamic: description
Dynamic: description-content-type
Dynamic: home-page
Dynamic: license
Dynamic: license-file
Dynamic: provides-extra
Dynamic: requires-dist
Dynamic: requires-python
Dynamic: summary
